contrib_extension/__init__.py
contrib_extension/_core.py
contrib_extension-0.0.1.1909230047rc0.dist-info/LICENSE
contrib_extension-0.0.1.1909230047rc0.dist-info/METADATA
contrib_extension-0.0.1.1909230047rc0.dist-info/WHEEL
contrib_extension-0.0.1.1909230047rc0.dist-info/top_level.txt
contrib_extension-0.0.1.1909230047rc0.dist-info/RECORD
