Metadata-Version: 2.1
Name: contrib-extension
Version: 0.0.1.1909230047rc0
Summary: contrib-extension
Home-page: https://github.com/Sotaneum/contrib-extension
Author: LEE Donggun
Author-email: gnyotnu39@gmail.com
License: MIT
Platform: UNKNOWN
Classifier: License :: OSI Approved :: MIT License
